setupext_gitversion-1.1.1-py2.7-nspkg.pth
setupext/gitversion.py
setupext_gitversion-1.1.1.dist-info/zip-safe
setupext_gitversion-1.1.1.dist-info/namespace_packages.txt
setupext_gitversion-1.1.1.dist-info/top_level.txt
setupext_gitversion-1.1.1.dist-info/entry_points.txt
setupext_gitversion-1.1.1.dist-info/METADATA
setupext_gitversion-1.1.1.dist-info/DESCRIPTION.rst
setupext_gitversion-1.1.1.dist-info/metadata.json
setupext_gitversion-1.1.1.dist-info/WHEEL
setupext_gitversion-1.1.1.dist-info/RECORD
