Metadata-Version: 2.0
Name: setupext-gitversion
Version: 1.1.1
Summary: PEP-440 compliant versioning helper
Home-page: http://github.com/dave-shawley/setupext-gitversion
Author: Dave Shawley
Author-email: daveshawley@gmail.com
License: UNKNOWN
Platform: any
Classifier: Intended Audience :: Developers
Classifier: License :: OSI Approved :: BSD License
Classifier: Operating System :: OS Independent
Classifier: Programming Language :: Python
Classifier: Programming Language :: Python :: 2
Classifier: Programming Language :: Python :: 2.6
Classifier: Programming Language :: Python :: 2.7
Classifier: Programming Language :: Python :: 3
Classifier: Programming Language :: Python :: 3.3
Classifier: Programming Language :: Python :: 3.4
Classifier: Programming Language :: Python :: Implementation :: CPython
Classifier: Programming Language :: Python :: Implementation :: PyPy
Classifier: Framework :: Setuptools Plugin
Classifier: Development Status :: 4 - Beta
Requires-Dist: packaging (>=14.5)
